ocryptor/__init__.py
ocryptor/main.py
oCrypt0r-1.0.9.post1.dist-info/LICENSE
oCrypt0r-1.0.9.post1.dist-info/METADATA
oCrypt0r-1.0.9.post1.dist-info/WHEEL
oCrypt0r-1.0.9.post1.dist-info/top_level.txt
oCrypt0r-1.0.9.post1.dist-info/RECORD
