Metadata-Version: 2.1
Name: oCrypt0r
Version: 1.0.9.post1
Summary: A minimalistic, simple AES encryption library written in python3.
Home-page: https://github.com/therealOri/oCrypt0r
Author: therealOri
Author-email: therealOri@duck.com
License: GPL-3.0
License-File: LICENSE
Requires-Dist: pycryptodome (==3.15.0)
